package_cb65/__init__.py
package_cb65/__main__.py
package_cb65/impl.py
package_cb65-0.0.9.dist-info/LICENSE
package_cb65-0.0.9.dist-info/METADATA
package_cb65-0.0.9.dist-info/WHEEL
package_cb65-0.0.9.dist-info/entry_points.txt
package_cb65-0.0.9.dist-info/top_level.txt
package_cb65-0.0.9.dist-info/RECORD
