Metadata-Version: 2.1
Name: package-cb65
Version: 0.0.9
Summary: Build a skeleton package.
Home-page: https://github.com/phfrohring/python
Author: Pierre-Henry Fröhring
Author-email: contact@phfrohring.com
License: UNKNOWN
Project-URL: Bug Tracker, https://github.com/phfrohring/python/issues
Platform: UNKNOWN
Classifier: Programming Language :: Python :: 3
Classifier: License :: OSI Approved :: MIT License
Classifier: Operating System :: OS Independent
Requires-Python: >=3.6
License-File: LICENSE
Requires-Dist: toolz
Requires-Dist: tools-09d3
